{
  "neoforge:conditions": [
    {
      "type": "alltuttasneeds:module_enabled",
      "module": "doors"
    },
    {
      "type": "neoforge:mod_loaded",
      "modid": "abundant_atmosphere"
    },
    {
      "type": "alltuttasneeds:door_set_enabled",
      "set": "consistent"
    }
  ],
  "parent": "minecraft:recipes/root",
  "criteria": {
    "has_ashroot_door": {
      "conditions": {
        "items": [
          {
            "items": "abundant_atmosphere:ashroot_indiscrete_door"
          }
        ]
      },
      "trigger": "minecraft:inventory_changed"
    },
    "has_the_recipe": {
      "conditions": {
        "recipe": "abundant_atmosphere:crafting/ashroot_normal_from_indiscrete"
      },
      "trigger": "minecraft:recipe_unlocked"
    }
  },
  "requirements": [
    [
      "has_the_recipe",
      "has_ashroot_door"
    ]
  ],
  "rewards": {
    "recipes": [
      "abundant_atmosphere:crafting/ashroot_normal_from_indiscrete"
    ]
  }
}